{
  "generated": "2026-07-22T15:17:42.655589Z",
  "generatedPT": "8:17 AM PT",
  "rightNow": [
    {
      "urgency": "week",
      "text": "Android v1 \u2014 port to Google Play",
      "jer": "JER-678",
      "pillar": "\ud83d\udcf1 Maddy's App"
    },
    {
      "urgency": "urgent",
      "text": "Reminders don't fire after setup (subject expected proactive nudges)",
      "jer": "JER-679",
      "pillar": ""
    },
    {
      "urgency": "urgent",
      "text": "Content series \u2014 men's physical health, performance + whole self (Fortify SX/PH)",
      "jer": "JER-148",
      "pillar": "Wealth Stack"
    }
  ],
  "contentDue": [],
  "followUpRadar": [
    {
      "name": "Jennifer Rendon",
      "days": 0,
      "why": ""
    },
    {
      "name": "Mike Ryan",
      "days": 0,
      "why": ""
    },
    {
      "name": "Corey Simpson",
      "days": 0,
      "why": ""
    },
    {
      "name": "Perry Swanson",
      "days": 117,
      "why": ""
    },
    {
      "name": "Adam Kohn",
      "days": 118,
      "why": ""
    },
    {
      "name": "Eric Stewart",
      "days": 118,
      "why": ""
    }
  ],
  "socialPulse": {
    "substack": {
      "subscribers": null,
      "posts": null
    },
    "linkedin": {
      "followers": null
    },
    "instagram": {
      "followers": null
    },
    "bluesky": {
      "followers": null
    },
    "youtube": {
      "subscribers": null
    }
  }
}